openvoicelab-0.0.1.dist-info/licenses/LICENSE
ovl/__init__.py
ovl/app.py
ovl/cli.py
ovl/models/base.py
ovl/models/vibevoice/__init__.py
ovl/models/vibevoice/model.py
ovl/models/vibevoice/voices.py
ovl/training/__init__.py
ovl/training/data_utils.py
ovl/training/train_script.py
ovl/training/trainer.py
ovl/ui/__init__.py
ovl/ui/data.py
ovl/ui/inference.py
ovl/ui/settings.py
ovl/ui/training.py
ovl/ui/voices.py
ovl/utils/__init__.py
ovl/utils/logging.py
openvoicelab-0.0.1.dist-info/METADATA
openvoicelab-0.0.1.dist-info/WHEEL
openvoicelab-0.0.1.dist-info/entry_points.txt
openvoicelab-0.0.1.dist-info/top_level.txt
openvoicelab-0.0.1.dist-info/RECORD
