Metadata-Version: 2.4
Name: openvoicelab
Version: 0.0.1
Classifier: Development Status :: 3 - Alpha
Classifier: Intended Audience :: Developers
Classifier: License :: OSI Approved :: MIT License
Classifier: Programming Language :: Python :: 3
Classifier: Programming Language :: Python :: 3.10
Classifier: Programming Language :: Python :: 3.11
Requires-Python: >=3.10
License-File: LICENSE
Requires-Dist: rich
Requires-Dist: gradio
Requires-Dist: torch
Requires-Dist: click
Dynamic: license-file
